{
  "schema": "avrxpu-run/1",
  "run_id": "cat1-11-ekf-i1-501853ba-1781453885",
  "workload": {
    "id": "11-ekf",
    "category": "cat1-estimation-control",
    "kernel": "EKF covariance predict (states 0..12), 24x24 fp32"
  },
  "kind": "measurement",
  "created_utc": "2026-06-14T16:18:05Z",
  "unixtime": 1781453885,
  "platform": {
    "runner": "navrobotec",
    "gem5_git": "2264c71015"
  },
  "build": {
    "mcu": "atmega1284p",
    "toolchain": "avr-gcc 7.3.0",
    "cflags": "-O1 -ffp-contract=off -fno-fast-math",
    "iters": 1,
    "trace": false,
    "elf": "ekf_avr_i1.elf",
    "elf_sha256": "501853baf36a48dd66cb841e51362c114f59d0da158bf4ae0877e3e3d38b46cd",
    "elf_archived": "cat1-estimation-control/11-ekf/elf/501853baf36a.elf"
  },
  "validation": {
    "host_crc": "26175af3",
    "gem5_crc": "26175af3",
    "checkpoints": 0,
    "match": true
  },
  "exit": {
    "cause": "AVR Syscall Exit",
    "ok": true
  },
  "metrics": {
    "simInsts": 800482,
    "simOps": 800482,
    "numCycles": 1022029,
    "cpi": 1.276767,
    "ipc": 0.783228,
    "mem_insts": 23773,
    "bytes_moved": 23773,
    "compute_insts": 776709,
    "insts_per_byte": 32.672
  },
  "opmix": {
    "available": true,
    "total": 800482,
    "classes": {
      "adc": 142234,
      "cpc": 68584,
      "brbs": 65976,
      "brbc": 59117,
      "add": 57168,
      "eor": 37066,
      "ror_inst": 34764,
      "cp": 28218,
      "sbc": 26613,
      "movw": 26143,
      "sbci": 22450,
      "cpi": 16797,
      "mov": 15951,
      "dec": 15393,
      "ret": 15391,
      "andi": 14568,
      "call": 13736,
      "mul": 13427,
      "ldi": 12774,
      "com": 12376,
      "subi": 12356,
      "sub": 11489,
      "lsr": 9486,
      "ldd_y": 8428,
      "and": 7901,
      "inc": 7563,
      "bst": 5532,
      "st_x_postinc": 5202,
      "sbrc": 4930,
      "st_z_postinc": 4608,
      "jmp": 4137,
      "bld": 3305,
      "neg": 2912,
      "rjmp": 2532,
      "or": 2477,
      "std_y": 1906,
      "rcall": 1656,
      "ld_x_postinc": 1096,
      "adiw": 807,
      "ldd_z": 776,
      "ld_z_postinc": 737,
      "sbiw": 647,
      "std_z": 576,
      "ld_x": 244,
      "sbrs": 178,
      "elpm_z_postinc": 116,
      "st_x": 38,
      "bclr": 26,
      "push": 24,
      "pop": 22,
      "out_instr": 13,
      "cpse": 9,
      "in_instr": 7
    }
  },
  "opmix_cycles": {
    "available": true,
    "total": 1022010,
    "classes": {
      "adc": 142234,
      "brbc": 110242,
      "brbs": 92010,
      "cpc": 68584,
      "ret": 61564,
      "add": 57168,
      "call": 54944,
      "eor": 37066,
      "ror_inst": 34764,
      "cp": 28218,
      "mul": 26854,
      "sbc": 26613,
      "movw": 26143,
      "sbci": 22450,
      "ldd_y": 16856,
      "cpi": 16797,
      "mov": 15951,
      "dec": 15393,
      "andi": 14568,
      "ldi": 12774,
      "jmp": 12411,
      "com": 12376,
      "subi": 12356,
      "sub": 11489,
      "st_x_postinc": 10404,
      "lsr": 9486,
      "sbrc": 9228,
      "st_z_postinc": 9216,
      "and": 7901,
      "inc": 7563,
      "bst": 5532,
      "rjmp": 5064,
      "rcall": 4968,
      "std_y": 3812,
      "bld": 3305,
      "neg": 2912,
      "or": 2477,
      "ld_x_postinc": 2192,
      "adiw": 1614,
      "ldd_z": 1552,
      "ld_z_postinc": 1474,
      "sbiw": 1294,
      "std_z": 1152,
      "ld_x": 488,
      "sbrs": 210,
      "elpm_z_postinc": 116,
      "st_x": 76,
      "push": 48,
      "pop": 44,
      "bclr": 26,
      "out_instr": 13,
      "cpse": 11,
      "in_instr": 7
    }
  },
  "funcmix": {
    "available": true,
    "total": 800482,
    "classes": {
      "__divsf3_pse": 203672,
      "main": 124614,
      "__mulsf3_pse": 91667,
      "__addsf3x": 78799,
      "__floatsisf": 52260,
      "__udivmodhi4_loop": 45952,
      "__udivmodhi4_ep": 40296,
      "__fp_round": 33500,
      "__fp_splitA": 33401,
      "__fp_split3": 26544,
      "__stack": 18680,
      ".do_clear_bss_start": 13828,
      "__addsf3": 6692,
      "__EEPROM_REGION_LENGTH__": 5717,
      ".do_clear_bss_loop": 4608,
      "_div": 3864,
      "__mulsf3": 3776,
      "__mulsf3x": 3202,
      "__udivmodhi4": 2208,
      "__fp_szero": 1860,
      "__USER_SIGNATURE_REGION_LENGTH__": 1456,
      "__divsf3": 1104,
      "__divsf3x": 1104,
      "__do_copy_data": 591,
      "__divmodhi4_exit": 552,
      "__subsf3": 378,
      "__DATA_REGION_LENGTH__": 119,
      "__fp_zero": 23,
      "__ctors_end": 6,
      "__do_clear_bss": 4,
      "ekf_predict": 4,
      "__heap_end": 1
    }
  },
  "funcmix_cycles": {
    "available": true,
    "total": 1022010,
    "classes": {
      "__divsf3_pse": 233106,
      "main": 147140,
      "__mulsf3_pse": 112826,
      "__addsf3x": 98802,
      "__floatsisf": 65111,
      "__udivmodhi4_loop": 53888,
      "__fp_round": 52630,
      "__udivmodhi4_ep": 50784,
      "__fp_splitA": 45726,
      "__stack": 32760,
      "__fp_split3": 30173,
      ".do_clear_bss_start": 18439,
      "__addsf3": 15057,
      "__mulsf3": 12355,
      "__EEPROM_REGION_LENGTH__": 9894,
      ".do_clear_bss_loop": 9216,
      "__mulsf3x": 8005,
      "_div": 7728,
      "__divsf3": 3864,
      "__fp_szero": 2790,
      "__udivmodhi4": 2760,
      "__divsf3x": 2760,
      "__USER_SIGNATURE_REGION_LENGTH__": 2546,
      "__divmodhi4_exit": 2208,
      "__do_copy_data": 824,
      "__subsf3": 378,
      "__DATA_REGION_LENGTH__": 195,
      "__fp_zero": 23,
      "ekf_predict": 8,
      "__ctors_end": 6,
      "__do_clear_bss": 5,
      "__heap_end": 3
    }
  },
  "raw": {
    "stats": "cat1-11-ekf-i1-501853ba-1781453885.stats.txt",
    "opmix": "cat1-11-ekf-i1-501853ba-1781453885.opmix.txt",
    "opmix_svg": "cat1-11-ekf-i1-501853ba-1781453885.opmix.svg",
    "cycles": "cat1-11-ekf-i1-501853ba-1781453885.cycles.txt",
    "cycles_svg": "cat1-11-ekf-i1-501853ba-1781453885.cycles.svg",
    "funcmix": "cat1-11-ekf-i1-501853ba-1781453885.funcmix.txt",
    "funcmix_svg": "cat1-11-ekf-i1-501853ba-1781453885.funcmix.svg",
    "funccyc": "cat1-11-ekf-i1-501853ba-1781453885.funccyc.txt",
    "funccyc_svg": "cat1-11-ekf-i1-501853ba-1781453885.funccyc.svg",
    "trace_cmp": "gem5_crc==host_crc"
  },
  "note": "EKF predict x1; fp32 softfloat; opmix+cycmix+funcmix+funccyc+arith axes"
}
